odoo/addons/hr_timesheet_type_non_billable/README.rst
odoo/addons/hr_timesheet_type_non_billable/__init__.py
odoo/addons/hr_timesheet_type_non_billable/__manifest__.py
odoo/addons/hr_timesheet_type_non_billable/i18n/ca.po
odoo/addons/hr_timesheet_type_non_billable/i18n/es.po
odoo/addons/hr_timesheet_type_non_billable/i18n/hr_timesheet_type_non_billable.pot
odoo/addons/hr_timesheet_type_non_billable/i18n/it.po
odoo/addons/hr_timesheet_type_non_billable/models/__init__.py
odoo/addons/hr_timesheet_type_non_billable/models/account_analytic_line.py
odoo/addons/hr_timesheet_type_non_billable/models/project_project.py
odoo/addons/hr_timesheet_type_non_billable/models/project_task.py
odoo/addons/hr_timesheet_type_non_billable/models/project_time_type.py
odoo/addons/hr_timesheet_type_non_billable/readme/CONTRIBUTORS.md
odoo/addons/hr_timesheet_type_non_billable/readme/DESCRIPTION.md
odoo/addons/hr_timesheet_type_non_billable/readme/USAGE.md
odoo/addons/hr_timesheet_type_non_billable/static/description/icon.png
odoo/addons/hr_timesheet_type_non_billable/static/description/index.html
odoo/addons/hr_timesheet_type_non_billable/tests/__init__.py
odoo/addons/hr_timesheet_type_non_billable/tests/test_hr_timesheet_type_non_billable.py
odoo/addons/hr_timesheet_type_non_billable/views/project_time_type_view.xml
odoo_addon_hr_timesheet_type_non_billable-17.0.1.0.0.13.dist-info/METADATA
odoo_addon_hr_timesheet_type_non_billable-17.0.1.0.0.13.dist-info/WHEEL
odoo_addon_hr_timesheet_type_non_billable-17.0.1.0.0.13.dist-info/top_level.txt
odoo_addon_hr_timesheet_type_non_billable-17.0.1.0.0.13.dist-info/RECORD
