Metadata-Version: 2.1
Name: odoo-addon-hr_timesheet_type_non_billable
Version: 17.0.1.0.0.13
Requires-Python: >=3.10
Requires-Dist: odoo-addon-hr_timesheet_time_type>=17.0dev,<17.1dev
Requires-Dist: odoo-addon-sale_timesheet_line_exclude>=17.0dev,<17.1dev
Requires-Dist: odoo>=17.0a,<17.1dev
Summary: HR Timesheet Type Non Billable
Home-page: https://github.com/OCA/timesheet
License: AGPL-3
Author: APSL-Nagarro, Odoo Community Association (OCA)
Author-email: support@odoo-community.org
Classifier: Programming Language :: Python
Classifier: Framework :: Odoo
Classifier: Framework :: Odoo :: 17.0
Classifier: License :: OSI Approved :: GNU Affero General Public License v3
